LICENSE.txt
MANIFEST.in
README
README.md
requirements.txt
setup.py
cfconfigurator/__init__.py
cfconfigurator/cf.py
cfconfigurator/exceptions.py
cfconfigurator/uaa.py
cfconfigurator.egg-info/PKG-INFO
cfconfigurator.egg-info/SOURCES.txt
cfconfigurator.egg-info/dependency_links.txt
cfconfigurator.egg-info/requires.txt
cfconfigurator.egg-info/top_level.txt