Metadata-Version: 1.1
Name: cfconfigurator
Version: 0.2.5
Summary: Simple and small library to manage Cloud Foundry
Home-page: https://github.com/SpringerPE/python-cfconfigurator
Author: Jose Riguera Lopez
Author-email: jose.riguera@springer.com
License: MIT
Download-URL: https://github.com/SpringerPE/python-cfconfigurator/releases/tag/v0.2.5
Keywords: cf cloudfoundry cloud foundry lib
Platform: UNKNOWN
Classifier: Development Status :: 4 - Beta
Classifier: Intended Audience :: System Administrators
Classifier: Topic :: System :: Systems Administration
Classifier: License :: OSI Approved :: MIT License
Classifier: Programming Language :: Python :: 2.7
Classifier: Programming Language :: Python :: 3
